code2npdoc.py
npdoc2md.py
npdoc2md-0.0.1.dist-info/LICENSE
npdoc2md-0.0.1.dist-info/METADATA
npdoc2md-0.0.1.dist-info/WHEEL
npdoc2md-0.0.1.dist-info/entry_points.txt
npdoc2md-0.0.1.dist-info/top_level.txt
npdoc2md-0.0.1.dist-info/RECORD
