Metadata-Version: 2.1
Name: npdoc2md
Version: 0.0.1
Summary: Scripts for autogenerating markdown docs from numpy-style docstrings.
Home-page: https://github.com/jwlodek/npdoc2md
Author: Jakub Wlodek
Author-email: jwlodek.dev@gmail.com
License: MIT
Keywords: markdown numpy docs autogenerate script
Platform: UNKNOWN
Classifier: Development Status :: 4 - Beta
Classifier: Intended Audience :: Developers
Classifier: Programming Language :: Python :: 3.5
Classifier: Programming Language :: Python :: 3.6
Classifier: Programming Language :: Python :: 3.7
Classifier: Programming Language :: Python :: 3.8
Requires-Python: >=3.5
